xaal/__init__.py
xaal/sensfloor/__init__.py
xaal/sensfloor/__main__.py
xaal/sensfloor/gw.py
xaal_sensfloor-0.2.2.dist-info/METADATA
xaal_sensfloor-0.2.2.dist-info/WHEEL
xaal_sensfloor-0.2.2.dist-info/top_level.txt
xaal_sensfloor-0.2.2.dist-info/RECORD
